firedx/__init__.py
firedx/attributes.py
firedx/bldg_fuel_models.py
firedx/bldg_fuel_models_mod.py
firedx/firedx.py
firedx/footprints.py
firedx/generate.py
firedx/mitigation.py
firedx/modify_fbfm.py
firedx/utils.py
firedx-0.1.1.dist-info/LICENSE
firedx-0.1.1.dist-info/METADATA
firedx-0.1.1.dist-info/WHEEL
firedx-0.1.1.dist-info/RECORD
