Metadata-Version: 2.3
Name: firedx
Version: 0.1.1
Summary: A data engine for modeling and analyzing fire hazard and risk to communities and built assets.
License: Proprietary
Author: Maria Faye Theodori
Author-email: theodori@berkeley.edu
Requires-Python: >=3.12
Classifier: License :: Other/Proprietary License
Classifier: Programming Language :: Python :: 3
Classifier: Programming Language :: Python :: 3.12
Classifier: Programming Language :: Python :: 3.13
Requires-Dist: geopandas
Requires-Dist: mercantile
Requires-Dist: numpy
Requires-Dist: openpyxl
Requires-Dist: osmnx
Requires-Dist: pandas
Requires-Dist: requests
Requires-Dist: tqdm
